{"doi":"10.1007/s11606-020-06583-7","slug":"cpd_2021","meta":{"doi":"10.1007/s11606-020-06583-7","popular":false,"authors":["melek-somai"],"excerpt":"The inclusion of PCD enhanced essential aspects of patient-provider communication but did not affect patient activation. Outcomes did not differ by race."},"content":"","citation":{"publisher":"Springer Science and Business Media LLC","issue":"11","DOI":"10.1007/s11606-020-06583-7","type":"article-journal","page":"3321-3329","source":"Crossref","title":"Impact of Pre-visit Contextual Data Collection on Patient-Physician Communication and Patient Activation: a Randomized Trial","volume":"36","author":[{"ORCID":"http://orcid.org/0000-0003-3392-0164","authenticated-orcid":false,"given":"Jeana M.","family":"Holt","sequence":"first","affiliation":[]},{"given":"Rachel","family":"Cusatis","sequence":"additional","affiliation":[]},{"given":"Aaron","family":"Winn","sequence":"additional","affiliation":[]},{"given":"Onur","family":"Asan","sequence":"additional","affiliation":[]},{"given":"Charles","family":"Spanbauer","sequence":"additional","affiliation":[]},{"given":"Joni S.","family":"Williams","sequence":"additional","affiliation":[]},{"given":"Kathryn E.","family":"Flynn","sequence":"additional","affiliation":[]},{"given":"Melek","family":"Somai","sequence":"additional","affiliation":[]},{"given":"AkkeNeel","family":"Talsma","sequence":"additional","affiliation":[]},{"given":"Purushottam","family":"Laud","sequence":"additional","affiliation":[]},{"given":"Gregory","family":"Makoul","sequence":"additional","affiliation":[]},{"given":"Bradley H.","family":"Crotty","sequence":"additional","affiliation":[]}],"container-title":"Journal of General Internal Medicine","language":"en","issued":{"date-parts":[[2021,2,9]]},"URL":"http://dx.doi.org/10.1007/s11606-020-06583-7","ISSN":"0884-8734","container-title-short":"J GEN INTERN MED","id":"temp_id_8354863230507632"},"publishedAt":{"text":"February 9, 2021","iso":"2021-02-08T23:00:00.000Z","timestamp":1612825200000,"relative":"2 years ago"},"publisher":"Journal of General Internal Medicine","url":"http://dx.doi.org/10.1007/s11606-020-06583-7"}